ms_mailbox_reader/__init__.py
ms_mailbox_reader/reader.py
ms_mailbox_reader-1.0.1.dist-info/LICENSE
ms_mailbox_reader-1.0.1.dist-info/METADATA
ms_mailbox_reader-1.0.1.dist-info/WHEEL
ms_mailbox_reader-1.0.1.dist-info/top_level.txt
ms_mailbox_reader-1.0.1.dist-info/RECORD
